teamcowboyapi/__init__.py
teamcowboyapi/exceptions.py
teamcowboyapi/tc_api.py
teamcowboyapi/tc_dataadapter.py
teamcowboyapi/tc_helpers.py
teamcowboyapi/objects/activitys/__init__.py
teamcowboyapi/objects/activitys/activity.py
teamcowboyapi/objects/attendances/__init__.py
teamcowboyapi/objects/attendances/attendancelist.py
teamcowboyapi/objects/authuser/__init__.py
teamcowboyapi/objects/authuser/authuser.py
teamcowboyapi/objects/colorswatches/__init__.py
teamcowboyapi/objects/colorswatches/colorswatch.py
teamcowboyapi/objects/errors/__init__.py
teamcowboyapi/objects/errors/error.py
teamcowboyapi/objects/events/__init__.py
teamcowboyapi/objects/events/event.py
teamcowboyapi/objects/events/rsvpinstance.py
teamcowboyapi/objects/events/saversvpresponce.py
teamcowboyapi/objects/locations/__init__.py
teamcowboyapi/objects/locations/location.py
teamcowboyapi/objects/messages/__init__.py
teamcowboyapi/objects/messages/message.py
teamcowboyapi/objects/messages/messagecomment.py
teamcowboyapi/objects/messages/postedby.py
teamcowboyapi/objects/photos/__init__.py
teamcowboyapi/objects/photos/profilephoto.py
teamcowboyapi/objects/seasons/__init__.py
teamcowboyapi/objects/seasons/season.py
teamcowboyapi/objects/teams/__init__.py
teamcowboyapi/objects/teams/team.py
teamcowboyapi/objects/teams/teammembertype.py
teamcowboyapi/objects/tests/__init__.py
teamcowboyapi/objects/tests/test.py
teamcowboyapi/objects/users/__init__.py
teamcowboyapi/objects/users/linkeduser.py
teamcowboyapi/objects/users/user.py
teamcowboyapi/objects/users/usermetainfo.py
python_teamcowboy_api-0.1.3.dist-info/LICENSE
python_teamcowboy_api-0.1.3.dist-info/METADATA
python_teamcowboy_api-0.1.3.dist-info/WHEEL
python_teamcowboy_api-0.1.3.dist-info/top_level.txt
python_teamcowboy_api-0.1.3.dist-info/RECORD
