Metadata-Version: 2.1
Name: python-teamcowboy-api
Version: 0.1.3
Summary: Teamcowboy python wrapper
Author-email: Kristian Nilssen <kristian.c.nilssen@gmail.com>
License: MIT License
Project-URL: Homepage, https://github.com/KCNilssen/TeamCowboyApi-Python
Project-URL: Bug Tracker, https://github.com/KCNilssen/TeamCowboyApi-Python/issues
Classifier: Programming Language :: Python :: 3
Classifier: License :: OSI Approved :: MIT License
Classifier: Operating System :: OS Independent
Requires-Python: >=3.10
License-File: LICENSE
Requires-Dist: requests (>=2)
Requires-Dist: requests-mock (>=1.10.0)
